Metadata-Version: 2.1
Name: surroopt
Version: 0.0.1
Summary: Python package of SurroOpt.
